Omnispindle/__init__.py
Omnispindle/__main__.py
Omnispindle/ai_assistant.py
Omnispindle/api_client.py
Omnispindle/api_tools.py
Omnispindle/auth.py
Omnispindle/auth_flow.py
Omnispindle/auth_setup.py
Omnispindle/auth_utils.py
Omnispindle/chat-to-create-todos-from-work.txt
Omnispindle/context.py
Omnispindle/database.py
Omnispindle/http_server.py
Omnispindle/hybrid_tools.py
Omnispindle/mcp_handler.py
Omnispindle/middleware.py
Omnispindle/mqtt.py
Omnispindle/patches.py
Omnispindle/requirements.txt
Omnispindle/scheduler.py
Omnispindle/server.py
Omnispindle/sse_handler.py
Omnispindle/stdio_http_server.py
Omnispindle/stdio_server.py
Omnispindle/todo_log_service.py
Omnispindle/token_exchange.py
Omnispindle/tools.py
Omnispindle/utils.py
Omnispindle/verify_token.py
Omnispindle/auth0_actions/custom_token_exchange.js
Omnispindle/models/__init__.py
Omnispindle/models/config.py
omnispindle-1.0.0.dist-info/METADATA
omnispindle-1.0.0.dist-info/WHEEL
omnispindle-1.0.0.dist-info/entry_points.txt
omnispindle-1.0.0.dist-info/RECORD
