Metadata-Version: 2.4
Name: omnispindle
Version: 1.0.0
Summary: API-first MCP Todo Server for AI agents with Auth0 integration
Project-URL: Homepage, https://github.com/DanEdens/Omnispindle
Project-URL: Repository, https://github.com/DanEdens/Omnispindle.git
Project-URL: Issues, https://github.com/DanEdens/Omnispindle/issues
Project-URL: Documentation, https://github.com/DanEdens/Omnispindle/blob/main/README.md
Author-email: Dan Edens <danedens31@gmail.com>
Maintainer-email: Dan Edens <danedens31@gmail.com>
License: MIT
Keywords: ai-agents,api-first,auth0,fastmcp,madness-interactive,mcp,model-context-protocol,task-management,todo
Classifier: Development Status :: 5 - Production/Stable
Classifier: Environment :: Console
Classifier: Environment :: Web Environment
Classifier: Framework :: FastAPI
Classifier: Intended Audience :: Developers
Classifier: License :: OSI Approved :: MIT License
Classifier: Operating System :: OS Independent
Classifier: Programming Language :: Python :: 3
Classifier: Programming Language :: Python :: 3.11
Classifier: Programming Language :: Python :: 3.12
Classifier: Programming Language :: Python :: 3.13
Classifier: Topic :: Internet :: WWW/HTTP :: HTTP Servers
Classifier: Topic :: Office/Business :: Scheduling
Classifier: Topic :: Scientific/Engineering :: Artificial Intelligence
Classifier: Topic :: Software Development :: Libraries :: Python Modules
Requires-Python: >=3.11
Requires-Dist: fastmcp>=0.1.0
Requires-Dist: httpx>=0.23.0
Requires-Dist: numpy>=1.20.0
Requires-Dist: paho-mqtt>=2.0.0
Requires-Dist: pymongo>=4.0.0
Requires-Dist: python-dateutil>=2.8.2
Requires-Dist: python-dotenv>=0.19.0
Requires-Dist: python-jose>=3.3.0
Requires-Dist: starlette>=0.17.1
Requires-Dist: uvicorn>=0.17.0
Provides-Extra: ai
Requires-Dist: lmstudio; extra == 'ai'
Requires-Dist: scikit-learn>=1.0.0; extra == 'ai'
Provides-Extra: dev
Requires-Dist: black>=22.0.0; extra == 'dev'
Requires-Dist: isort>=5.10.0; extra == 'dev'
Requires-Dist: mypy>=1.0.0; extra == 'dev'
Requires-Dist: pytest-asyncio>=0.21.0; extra == 'dev'
Requires-Dist: pytest>=7.0.0; extra == 'dev'
